seq_pipeline/__init__.py
seq_pipeline/__main__.py
seq_pipeline/config.py
seq_pipeline/launch.py
seq_pipeline/process.py
seq_pipeline/util.py
seq_pipeline/pipelines/atac.sh
seq_pipeline/pipelines/atac_lab.sh
seq_pipeline/pipelines/bigbed.sh
seq_pipeline/pipelines/bigwig.sh
seq_pipeline/pipelines/bigwig_lab.sh
seq_pipeline/pipelines/bis.sh
seq_pipeline/pipelines/cage.sh
seq_pipeline/pipelines/chip.sh
seq_pipeline/pipelines/chip_lab.sh
seq_pipeline/pipelines/chip_lab_quick.sh
seq_pipeline/pipelines/chip_se.sh
seq_pipeline/pipelines/chip_se_lab.sh
seq_pipeline/pipelines/chip_se_lab_quick.sh
seq_pipeline/pipelines/edd.sh
seq_pipeline/pipelines/peak_calling.sh
seq_pipeline/pipelines/peak_calling_lab.sh
seq_pipeline/pipelines/rna.sh
seq_pipeline-0.0.10.dist-info/METADATA
seq_pipeline-0.0.10.dist-info/WHEEL
seq_pipeline-0.0.10.dist-info/licenses/LICENSE
seq_pipeline-0.0.10.dist-info/RECORD
