Metadata-Version: 2.1
Name: seq_pipeline
Version: 0.0.10
Summary: Pipelines to process genome-wide sequencing
Project-URL: Homepage, https://github.com/ajgouhier/seq_pipeline
Author-email: Arthur Gouhier <ajgouhier@gmail.com>
License: MIT
License-File: LICENSE
Classifier: License :: OSI Approved :: MIT License
Classifier: Operating System :: OS Independent
Classifier: Programming Language :: Python :: 3
Requires-Python: >=3.8
